pytest_wiretap.py
pytest_wiretap-0.1.0.dev1.dist-info/METADATA
pytest_wiretap-0.1.0.dev1.dist-info/WHEEL
pytest_wiretap-0.1.0.dev1.dist-info/entry_points.txt
pytest_wiretap-0.1.0.dev1.dist-info/top_level.txt
pytest_wiretap-0.1.0.dev1.dist-info/RECORD
