Metadata-Version: 2.1
Name: pytest-wiretap
Version: 0.1.0.dev1
Summary: `pytest` plugin for recording call stacks
Author-email: Conrad Bzura <conradbzura@gmail.com>
License: MIT License
Classifier: Framework :: Pytest
Classifier: Programming Language :: Python :: 3.8
Classifier: Programming Language :: Python :: 3.9
Classifier: Programming Language :: Python :: 3.10
Classifier: Programming Language :: Python :: 3.11
Classifier: Programming Language :: Python :: 3.12
Classifier: Programming Language :: Python :: 3.13
Requires-Python: >=3.8
Requires-Dist: pytest
